{
    "skeleton": {
        "hash": "nfLRAVjJuRI",
        "spine": "4.0-from-4.1.23",
        "x": -952.94,
        "y": -134,
        "width": 2005.44,
        "height": 268
    },
    "bones": [
        {
            "name": "root"
        },
        {
            "name": "a01_feng_a",
            "parent": "root",
            "x": 29.66,
            "y": -45.64
        },
        {
            "name": "a01_feng_a2",
            "parent": "a01_feng_a",
            "length": 176.95,
            "rotation": 29.3,
            "x": -908.89,
            "y": 22.46
        },
        {
            "name": "a01_feng_a3",
            "parent": "a01_feng_a2",
            "length": 179.16,
            "rotation": -16.61,
            "x": 176.95
        },
        {
            "name": "a01_feng_a4",
            "parent": "a01_feng_a3",
            "length": 179.68,
            "rotation": -15.2,
            "x": 183.77,
            "y": -1.04
        },
        {
            "name": "a01_feng_a5",
            "parent": "a01_feng_a4",
            "length": 171.81,
            "rotation": -15.09,
            "x": 179.68
        },
        {
            "name": "a01_feng_a6",
            "parent": "a01_feng_a5",
            "length": 145.91,
            "rotation": -11.45,
            "x": 171.81
        },
        {
            "name": "a01_feng_a7",
            "parent": "a01_feng_a6",
            "length": 156.47,
            "rotation": 8.43,
            "x": 145.91
        },
        {
            "name": "a01_feng_a8",
            "parent": "a01_feng_a7",
            "length": 170.79,
            "rotation": 8.38,
            "x": 156.47
        },
        {
            "name": "a01_feng_a9",
            "parent": "a01_feng_a8",
            "length": 167.1,
            "rotation": 9.54,
            "x": 170.79
        },
        {
            "name": "a01_feng_a10",
            "parent": "a01_feng_a9",
            "length": 149.42,
            "rotation": 10.57,
            "x": 167.1
        },
        {
            "name": "a01_feng_a11",
            "parent": "a01_feng_a10",
            "length": 106.58,
            "rotation": 4.93,
            "x": 149.42
        },
        {
            "name": "a01_feng_a12",
            "parent": "a01_feng_a11",
            "length": 92.15,
            "rotation": 4.08,
            "x": 106.58
        },
        {
            "name": "a01_feng_a13",
            "parent": "a01_feng_a12",
            "length": 74.02,
            "rotation": 6.95,
            "x": 92.15
        },
        {
            "name": "a01_feng_a14",
            "parent": "a01_feng_a13",
            "length": 86.96,
            "rotation": 7.84,
            "x": 74.02
        },
        {
            "name": "a01_feng_a15",
            "parent": "a01_feng_a14",
            "length": 128.86,
            "rotation": 6.88,
            "x": 86.96
        },
        {
            "name": "a01_feng_a16",
            "parent": "root",
            "x": -559.17,
            "y": -5.38
        },
        {
            "name": "a01_feng_a17",
            "parent": "a01_feng_a16",
            "length": 97.12,
            "rotation": -0.53,
            "x": -375.89,
            "y": -55.75
        },
        {
            "name": "a01_feng_a18",
            "parent": "a01_feng_a17",
            "length": 87.24,
            "rotation": 8.83,
            "x": 97.12
        },
        {
            "name": "a01_feng_a19",
            "parent": "a01_feng_a18",
            "length": 98.81,
            "rotation": 4.85,
            "x": 87.24
        },
        {
            "name": "a01_feng_a20",
            "parent": "a01_feng_a19",
            "length": 83.64,
            "rotation": 3.73,
            "x": 98.81
        },
        {
            "name": "a01_feng_a21",
            "parent": "a01_feng_a20",
            "length": 84.44,
            "rotation": -8.92,
            "x": 83.64
        },
        {
            "name": "a01_feng_a22",
            "parent": "a01_feng_a21",
            "length": 110.62,
            "rotation": -8.89,
            "x": 85.34,
            "y": -0.12
        },
        {
            "name": "a01_feng_a23",
            "parent": "a01_feng_a22",
            "length": 72,
            "rotation": -8.41,
            "x": 110.62
        },
        {
            "name": "a01_feng_a24",
            "parent": "a01_feng_a23",
            "length": 65.79,
            "rotation": -12.31,
            "x": 72
        }
    ],
    "slots": [
        {
            "name": "a01_feng_a",
            "bone": "a01_feng_a2",
            "attachment": "a01_feng_a"
        },
        {
            "name": "a01_feng_a2",
            "bone": "a01_feng_a17",
            "attachment": "a01_feng_a"
        }
    ],
    "skins": [
        {
            "name": "default",
            "attachments": {
                "a01_feng_a": {
                    "a01_feng_a": {
                        "type": "mesh",
                        "uvs": [
                            0.06493,
                            0.65526,
                            0.08921,
                            0.4244,
                            0.13042,
                            0.21361,
                            0.17483,
                            0.08061,
                            0.21668,
                            0.00784,
                            0.25662,
                            0,
                            0.30614,
                            0,
                            0.35342,
                            0.01537,
                            0.39975,
                            0.09316,
                            0.44365,
                            0.24372,
                            0.47752,
                            0.37421,
                            0.5149,
                            0.5323,
                            0.55228,
                            0.67534,
                            0.59285,
                            0.7732,
                            0.64362,
                            0.86605,
                            0.68419,
                            0.88864,
                            0.72668,
                            0.87358,
                            0.76087,
                            0.84096,
                            0.8008,
                            0.77822,
                            0.83586,
                            0.69792,
                            0.87292,
                            0.56242,
                            0.92404,
                            0.36167,
                            0.95503,
                            0.17848,
                            0.98729,
                            0,
                            1,
                            0.04548,
                            1,
                            0.36167,
                            1,
                            0.54736,
                            0.96461,
                            0.65526,
                            0.90646,
                            0.6377,
                            0.87324,
                            0.75815,
                            0.83586,
                            0.84347,
                            0.80103,
                            0.92879,
                            0.76557,
                            0.97897,
                            0.71943,
                            1,
                            0.67982,
                            1,
                            0.64499,
                            1,
                            0.60282,
                            1,
                            0.55618,
                            0.96141,
                            0.50139,
                            0.8535,
                            0.46529,
                            0.74309,
                            0.4244,
                            0.61511,
                            0.37829,
                            0.49933,
                            0.35368,
                            0.41401,
                            0.32685,
                            0.32117,
                            0.2834,
                            0.276,
                            0.24269,
                            0.25592,
                            0.19988,
                            0.26847,
                            0.16122,
                            0.35128,
                            0.13119,
                            0.44162,
                            0.10531,
                            0.55203,
                            0.08167,
                            0.68252,
                            0.07093,
                            0.71355
                        ],
                        "triangles": [
                            23,
                            24,
                            25,
                            22,
                            23,
                            25,
                            27,
                            22,
                            25,
                            26,
                            27,
                            25,
                            21,
                            22,
                            27,
                            28,
                            21,
                            27,
                            28,
                            20,
                            21,
                            29,
                            20,
                            28,
                            19,
                            20,
                            29,
                            30,
                            19,
                            29,
                            18,
                            19,
                            30,
                            31,
                            18,
                            30,
                            17,
                            18,
                            31,
                            32,
                            17,
                            31,
                            33,
                            15,
                            16,
                            32,
                            33,
                            16,
                            32,
                            16,
                            17,
                            34,
                            35,
                            14,
                            36,
                            14,
                            35,
                            15,
                            34,
                            14,
                            34,
                            15,
                            33,
                            37,
                            12,
                            13,
                            38,
                            12,
                            37,
                            36,
                            13,
                            14,
                            37,
                            13,
                            36,
                            39,
                            10,
                            11,
                            38,
                            39,
                            11,
                            38,
                            11,
                            12,
                            9,
                            40,
                            8,
                            40,
                            9,
                            10,
                            39,
                            40,
                            10,
                            43,
                            6,
                            7,
                            42,
                            7,
                            8,
                            43,
                            7,
                            42,
                            41,
                            42,
                            8,
                            40,
                            41,
                            8,
                            45,
                            4,
                            5,
                            44,
                            5,
                            6,
                            45,
                            5,
                            44,
                            44,
                            6,
                            43,
                            46,
                            3,
                            4,
                            46,
                            4,
                            45,
                            47,
                            2,
                            3,
                            47,
                            3,
                            46,
                            48,
                            2,
                            47,
                            1,
                            2,
                            48,
                            49,
                            1,
                            48,
                            50,
                            0,
                            1,
                            49,
                            50,
                            1,
                            51,
                            0,
                            50
                        ],
                        "vertices": [
                            1,
                            2,
                            -40.93,
                            1.84,
                            1,
                            1,
                            2,
                            33.92,
                            30.79,
                            1,
                            3,
                            2,
                            137.22,
                            37.59,
                            0.98703,
                            3,
                            -48.82,
                            24.66,
                            0.01297,
                            12,
                            -1327.25,
                            569.89,
                            0,
                            2,
                            3,
                            50.21,
                            38.9,
                            1,
                            12,
                            -1227.45,
                            576.84,
                            0,
                            1,
                            3,
                            140.44,
                            38.56,
                            1,
                            2,
                            3,
                            222.91,
                            22.14,
                            0.02676,
                            4,
                            31.69,
                            32.64,
                            0.97324,
                            2,
                            4,
                            135.83,
                            37.2,
                            1,
                            12,
                            -956.69,
                            517.22,
                            0,
                            3,
                            4,
                            235.45,
                            37.45,
                            0.01284,
                            5,
                            44.09,
                            50.68,
                            0.98716,
                            12,
                            -862.65,
                            484.37,
                            0,
                            2,
                            5,
                            143.34,
                            60.3,
                            0.8736,
                            6,
                            -39.87,
                            53.45,
                            0.1264,
                            3,
                            5,
                            243.65,
                            49.79,
                            0.00048,
                            6,
                            60.52,
                            63.06,
                            0.99952,
                            13,
                            -740.15,
                            463.63,
                            0,
                            4,
                            6,
                            139.82,
                            67.11,
                            0.55124,
                            7,
                            3.82,
                            67.28,
                            0.44876,
                            13,
                            -689.08,
                            402.83,
                            0,
                            14,
                            -701.05,
                            503.12,
                            0,
                            5,
                            6,
                            229.18,
                            68.29,
                            0.00017,
                            7,
                            92.39,
                            55.34,
                            0.99983,
                            12,
                            -577.64,
                            253.07,
                            0,
                            13,
                            -634.23,
                            332.28,
                            0,
                            14,
                            -656.34,
                            425.74,
                            0,
                            5,
                            7,
                            179.53,
                            47.18,
                            0.23496,
                            8,
                            29.69,
                            43.31,
                            0.76504,
                            12,
                            -513.48,
                            193.53,
                            0,
                            13,
                            -577.76,
                            265.41,
                            0,
                            14,
                            -609.5,
                            351.8,
                            0,
                            3,
                            8,
                            118.72,
                            35.79,
                            1,
                            13,
                            -510.23,
                            206.9,
                            0,
                            14,
                            -550.59,
                            284.63,
                            0,
                            2,
                            9,
                            62.49,
                            24.11,
                            0.99996,
                            10,
                            -98.41,
                            42.89,
                            4e-05,
                            4,
                            9,
                            148.09,
                            22.09,
                            0.90913,
                            10,
                            -14.63,
                            25.2,
                            0.09087,
                            13,
                            -346.88,
                            100.9,
                            0,
                            14,
                            -403.21,
                            157.35,
                            0,
                            3,
                            9,
                            237.24,
                            30.33,
                            8e-05,
                            10,
                            74.52,
                            16.94,
                            0.99992,
                            12,
                            -177.63,
                            36.05,
                            0,
                            3,
                            10,
                            147,
                            15.74,
                            0.51445,
                            11,
                            -1.06,
                            15.89,
                            0.48555,
                            14,
                            -259.14,
                            83.47,
                            0,
                            2,
                            11,
                            84.64,
                            13.66,
                            1,
                            14,
                            -178.77,
                            53.63,
                            0,
                            2,
                            12,
                            55.96,
                            14.34,
                            1,
                            14,
                            -104.67,
                            33.2,
                            0,
                            2,
                            13,
                            51.84,
                            20.31,
                            0.99913,
                            14,
                            -19.21,
                            23.14,
                            0.00087,
                            2,
                            14,
                            100.62,
                            12.43,
                            0.05452,
                            15,
                            15.04,
                            10.7,
                            0.94548,
                            1,
                            15,
                            96.66,
                            8.44,
                            1,
                            1,
                            15,
                            179.59,
                            3.52,
                            1,
                            1,
                            15,
                            192.91,
                            -22.68,
                            1,
                            1,
                            15,
                            140.1,
                            -88.95,
                            1,
                            1,
                            15,
                            109.08,
                            -127.87,
                            1,
                            2,
                            14,
                            131.98,
                            -99.39,
                            0.05254,
                            15,
                            32.8,
                            -104.06,
                            0.94746,
                            2,
                            14,
                            30.29,
                            -31.11,
                            0.97445,
                            15,
                            -59.99,
                            -24.1,
                            0.02555,
                            2,
                            11,
                            234.52,
                            -14.89,
                            0,
                            13,
                            31.25,
                            -27.95,
                            1,
                            2,
                            12,
                            44.62,
                            -22.98,
                            1,
                            14,
                            -125.15,
                            0,
                            0,
                            1,
                            11,
                            76.17,
                            -25.8,
                            1,
                            4,
                            10,
                            151.75,
                            -22.25,
                            0.37987,
                            11,
                            0.4,
                            -22.37,
                            0.62013,
                            12,
                            -107.5,
                            -14.75,
                            0,
                            13,
                            -199.97,
                            9.52,
                            0,
                            3,
                            10,
                            54.77,
                            -14.53,
                            1,
                            13,
                            -291.08,
                            43.62,
                            0,
                            14,
                            -355.75,
                            92.99,
                            0,
                            2,
                            9,
                            140.3,
                            -8.16,
                            1,
                            12,
                            -281.86,
                            32.29,
                            0,
                            4,
                            9,
                            67.08,
                            -11.61,
                            1,
                            12,
                            -352,
                            53.58,
                            0,
                            13,
                            -434.41,
                            106.95,
                            0,
                            14,
                            -489.1,
                            175.27,
                            0,
                            3,
                            8,
                            152.12,
                            -19.16,
                            1,
                            13,
                            -515.6,
                            142.83,
                            0,
                            14,
                            -564.65,
                            221.89,
                            0,
                            1,
                            8,
                            53.97,
                            -29.87,
                            1,
                            1,
                            7,
                            96.1,
                            -35.24,
                            1,
                            2,
                            6,
                            165.33,
                            -31.81,
                            0.16852,
                            7,
                            14.55,
                            -34.31,
                            0.83148,
                            3,
                            5,
                            235.11,
                            -57.34,
                            0.00186,
                            6,
                            73.43,
                            -43.63,
                            0.99814,
                            12,
                            -766.37,
                            287.17,
                            0,
                            5,
                            5,
                            133.21,
                            -57.12,
                            0.88085,
                            6,
                            -26.49,
                            -63.65,
                            0.11915,
                            12,
                            -850.24,
                            345.06,
                            0,
                            13,
                            -893.7,
                            456.59,
                            0,
                            14,
                            -896.43,
                            584.27,
                            0,
                            5,
                            4,
                            240.68,
                            -69.26,
                            0.00048,
                            5,
                            76.93,
                            -50.99,
                            0.99952,
                            12,
                            -893.15,
                            381.98,
                            0,
                            13,
                            -931.83,
                            498.43,
                            0,
                            14,
                            -928.5,
                            630.92,
                            0,
                            4,
                            4,
                            183.15,
                            -46.88,
                            0.33038,
                            5,
                            15.56,
                            -44.36,
                            0.66962,
                            13,
                            -973.44,
                            544.02,
                            0,
                            14,
                            -963.51,
                            681.76,
                            0,
                            3,
                            4,
                            91.25,
                            -38.79,
                            1,
                            13,
                            -1052.21,
                            592.06,
                            0,
                            14,
                            -1034.99,
                            740.09,
                            0,
                            6,
                            2,
                            337.76,
                            -87.96,
                            0,
                            3,
                            179.24,
                            -38.33,
                            0.44049,
                            4,
                            5.41,
                            -37.17,
                            0.55951,
                            12,
                            -1104.41,
                            490.39,
                            0,
                            13,
                            -1128.41,
                            631.61,
                            0,
                            14,
                            -1105.08,
                            789.67,
                            0,
                            4,
                            2,
                            257.53,
                            -46.79,
                            0.0001,
                            3,
                            90.59,
                            -21.81,
                            0.9999,
                            13,
                            -1212.2,
                            664.96,
                            0,
                            14,
                            -1183.54,
                            834.13,
                            0,
                            4,
                            2,
                            175.7,
                            -26.32,
                            0.4448,
                            3,
                            6.33,
                            -25.58,
                            0.5552,
                            13,
                            -1295.6,
                            677.55,
                            0,
                            14,
                            -1264.45,
                            857.97,
                            0,
                            3,
                            2,
                            108.73,
                            -16.49,
                            1,
                            13,
                            -1363.21,
                            680.95,
                            0,
                            14,
                            -1330.96,
                            870.56,
                            0,
                            2,
                            2,
                            46.74,
                            -15.64,
                            1,
                            13,
                            -1424.99,
                            675.9,
                            0,
                            1,
                            2,
                            -13.77,
                            -21.78,
                            1,
                            1,
                            2,
                            -37.55,
                            -17.96,
                            1
                        ],
                        "hull": 52
                    }
                },
                "a01_feng_a2": {
                    "a01_feng_a": {
                        "type": "mesh",
                        "uvs": [
                            0.0473,
                            0.73052,
                            0.07796,
                            0.7847,
                            0.11896,
                            0.80577,
                            0.15231,
                            0.76363,
                            0.1937,
                            0.70342,
                            0.23279,
                            0.63419,
                            0.27801,
                            0.56796,
                            0.3125,
                            0.56495,
                            0.35083,
                            0.60409,
                            0.39107,
                            0.70041,
                            0.39413,
                            0.59807,
                            0.35658,
                            0.45057,
                            0.31787,
                            0.36026,
                            0.28338,
                            0.33919,
                            0.24314,
                            0.37531,
                            0.20558,
                            0.45358,
                            0.1638,
                            0.56194,
                            0.12663,
                            0.61914,
                            0.10133,
                            0.65827,
                            0.07642,
                            0.70342
                        ],
                        "triangles": [
                            8,
                            11,
                            10,
                            9,
                            8,
                            10,
                            11,
                            8,
                            12,
                            7,
                            13,
                            12,
                            8,
                            7,
                            12,
                            6,
                            14,
                            13,
                            6,
                            13,
                            7,
                            5,
                            15,
                            14,
                            5,
                            14,
                            6,
                            4,
                            16,
                            15,
                            4,
                            15,
                            5,
                            3,
                            17,
                            16,
                            3,
                            16,
                            4,
                            2,
                            18,
                            17,
                            2,
                            17,
                            3,
                            1,
                            18,
                            2,
                            1,
                            19,
                            18,
                            0,
                            19,
                            1
                        ],
                        "vertices": [
                            1,
                            17,
                            -17.87,
                            -0.8,
                            1,
                            1,
                            17,
                            46.8,
                            -14.73,
                            1,
                            1,
                            18,
                            32.61,
                            -24.87,
                            1,
                            2,
                            18,
                            103.69,
                            -23.83,
                            0.09073,
                            19,
                            14.38,
                            -25.13,
                            0.90927,
                            2,
                            19,
                            102.89,
                            -29.24,
                            0.42898,
                            20,
                            2.17,
                            -29.45,
                            0.57102,
                            2,
                            20,
                            86.3,
                            -35.58,
                            0.34162,
                            21,
                            8.14,
                            -34.74,
                            0.65838,
                            2,
                            21,
                            104.88,
                            -30.34,
                            0.09837,
                            22,
                            23.98,
                            -26.83,
                            0.90163,
                            2,
                            22,
                            96.56,
                            -24.85,
                            0.83663,
                            23,
                            -10.28,
                            -26.64,
                            0.16337,
                            2,
                            23,
                            71.03,
                            -23.88,
                            0.46303,
                            24,
                            4.15,
                            -23.54,
                            0.53697,
                            1,
                            24,
                            92.4,
                            -16.28,
                            1,
                            1,
                            24,
                            88.28,
                            11.6,
                            1,
                            2,
                            23,
                            76.29,
                            18.68,
                            0.42209,
                            24,
                            0.21,
                            19.16,
                            0.57791,
                            2,
                            22,
                            106.96,
                            30.19,
                            0.68563,
                            23,
                            -8.04,
                            29.33,
                            0.31437,
                            2,
                            21,
                            124.55,
                            28.82,
                            0.00185,
                            22,
                            34.27,
                            34.66,
                            0.99815,
                            1,
                            21,
                            39.32,
                            30.96,
                            1,
                            1,
                            20,
                            45.54,
                            27.37,
                            1,
                            1,
                            19,
                            50.24,
                            21.99,
                            1,
                            1,
                            18,
                            55.8,
                            22.29,
                            1,
                            2,
                            17,
                            95.69,
                            19.61,
                            0.43512,
                            18,
                            1.6,
                            19.6,
                            0.56488,
                            1,
                            17,
                            43.37,
                            7.02,
                            1
                        ],
                        "hull": 20
                    }
                }
            }
        }
    ],
    "animations": {
        "animation": {}
    },
    "extra": {
        "a01_feng_a2": {
            "rootBoneName": "a01_feng_a2",
            "animation": {
                "default": {
                    "name": "default",
                    "mode": 1,
                    "rotateCenter": 0,
                    "rotateTime": 8,
                    "rotateRange": 1,
                    "rotateOffset": 0,
                    "childOffset": 0.8450000000000001,
                    "spring": 0,
                    "affectByLevel": 0.3,
                    "springLevel": 0.101,
                    "scaleYRange": 0.01,
                    "scaleYTime": 6,
                    "scaleYOffset": 0,
                    "scaleYChildOffset": 0.5,
                    "scaleYCenter": 0,
                    "scaleYSpring": 0,
                    "scaleYAffectByLevel": 0.1
                }
            }
        },
        "a01_feng_a": {
            "rootBoneName": "a01_feng_a",
            "animation": {
                "default": {
                    "name": "default",
                    "mode": 3,
                    "moveXFreq": 6,
                    "moveXAmp": 50,
                    "moveXOctaves": 0,
                    "moveXDelay": 0,
                    "moveXCenter": 0,
                    "moveYFreq": 6,
                    "moveYAmp": 20,
                    "moveYOctaves": 0,
                    "moveYDelay": 2,
                    "moveYCenter": 0
                }
            }
        },
        "a01_feng_a17": {
            "rootBoneName": "a01_feng_a17",
            "animation": {
                "default": {
                    "name": "default",
                    "mode": 1,
                    "rotateCenter": 0,
                    "rotateTime": 6,
                    "rotateRange": 2,
                    "rotateOffset": 0.47417981376014273,
                    "childOffset": 0.8450000000000001,
                    "spring": 0,
                    "affectByLevel": 0.3,
                    "springLevel": 0.101
                }
            }
        },
        "a01_feng_a16": {
            "rootBoneName": "a01_feng_a16",
            "animation": {
                "default": {
                    "name": "default",
                    "mode": 3,
                    "moveXFreq": 5,
                    "moveXAmp": 30,
                    "moveXOctaves": 0,
                    "moveXDelay": -5.838840986012821,
                    "moveXCenter": 0,
                    "moveYFreq": 1,
                    "moveYAmp": 0,
                    "moveYOctaves": 0,
                    "moveYDelay": -4.085245493356086,
                    "moveYCenter": 0
                }
            }
        }
    },
    "extraSlot": {},
    "extraConfig": {
        "timeScale": 1
    }
}