{
    "skeleton": {
        "hash": "fTxxGj7/hyo",
        "spine": "4.0-from-4.1.23",
        "x": -847.5,
        "y": -467,
        "width": 1695,
        "height": 934
    },
    "bones": [
        {
            "name": "root"
        },
        {
            "name": "b11_yun_a",
            "parent": "root",
            "x": -306.29,
            "y": -430.89
        },
        {
            "name": "b11_yun_a2",
            "parent": "root",
            "x": 515.31,
            "y": -154.43
        },
        {
            "name": "b11_yun_a3",
            "parent": "root",
            "x": 351.77,
            "y": 114.25
        },
        {
            "name": "b11_yun_a4",
            "parent": "root",
            "x": 800.86,
            "y": 315.43
        }
    ],
    "slots": [
        {
            "name": "b11_yun_a",
            "bone": "b11_yun_a",
            "attachment": "b11_yun_a"
        }
    ],
    "skins": [
        {
            "name": "default",
            "attachments": {
                "b11_yun_a": {
                    "b11_yun_a": {
                        "type": "mesh",
                        "uvs": [
                            0,
                            0.99981,
                            0.22029,
                            0.91995,
                            0.35231,
                            0.83101,
                            0.41533,
                            0.70214,
                            0.51334,
                            0.6495,
                            0.60936,
                            0.66584,
                            0.68637,
                            0.60594,
                            0.71038,
                            0.52608,
                            0.64937,
                            0.52426,
                            0.58035,
                            0.46981,
                            0.63936,
                            0.31916,
                            0.73638,
                            0.23385,
                            0.8244,
                            0.21206,
                            0.90041,
                            0.13402,
                            1,
                            0,
                            1,
                            0.39357,
                            0.94742,
                            0.4208,
                            0.88841,
                            0.43351,
                            0.8394,
                            0.43351,
                            0.8294,
                            0.4517,
                            0.87876,
                            0.48259,
                            0.93097,
                            0.53099,
                            0.94799,
                            0.62779,
                            0.89352,
                            0.74827,
                            0.77549,
                            0.81315,
                            0.67335,
                            0.80697,
                            0.58199,
                            0.81727,
                            0.49368,
                            0.87487,
                            0.42558,
                            0.93666,
                            0.34898,
                            0.99123,
                            0.28486,
                            1,
                            0.76573,
                            0.66256,
                            0.84154,
                            0.60003,
                            0.77186,
                            0.48052,
                            0.7106,
                            0.39436
                        ],
                        "triangles": [
                            0,
                            1,
                            30,
                            29,
                            30,
                            2,
                            29,
                            2,
                            28,
                            2,
                            30,
                            1,
                            27,
                            28,
                            3,
                            28,
                            2,
                            3,
                            27,
                            4,
                            26,
                            27,
                            3,
                            4,
                            26,
                            5,
                            25,
                            26,
                            4,
                            5,
                            25,
                            31,
                            24,
                            23,
                            31,
                            32,
                            23,
                            24,
                            31,
                            25,
                            6,
                            31,
                            25,
                            5,
                            6,
                            23,
                            32,
                            22,
                            21,
                            32,
                            20,
                            32,
                            21,
                            22,
                            6,
                            7,
                            31,
                            31,
                            33,
                            32,
                            31,
                            7,
                            33,
                            33,
                            19,
                            32,
                            32,
                            19,
                            20,
                            7,
                            34,
                            33,
                            7,
                            8,
                            34,
                            9,
                            10,
                            8,
                            8,
                            10,
                            34,
                            19,
                            33,
                            18,
                            11,
                            18,
                            33,
                            13,
                            16,
                            17,
                            33,
                            34,
                            11,
                            11,
                            12,
                            18,
                            17,
                            18,
                            12,
                            17,
                            12,
                            13,
                            16,
                            13,
                            15,
                            34,
                            10,
                            11,
                            13,
                            14,
                            15
                        ],
                        "vertices": [
                            1,
                            1,
                            -541.21,
                            -35.93,
                            1,
                            1,
                            1,
                            -167.82,
                            38.66,
                            1,
                            2,
                            1,
                            55.96,
                            121.73,
                            0.9213,
                            2,
                            -765.64,
                            -154.73,
                            0.0787,
                            2,
                            1,
                            162.77,
                            242.09,
                            0.75004,
                            2,
                            -658.83,
                            -34.37,
                            0.24996,
                            2,
                            1,
                            328.91,
                            291.26,
                            0.56785,
                            2,
                            -492.7,
                            14.8,
                            0.43215,
                            3,
                            1,
                            491.65,
                            276,
                            0.32075,
                            2,
                            -329.95,
                            -0.46,
                            0.67061,
                            3,
                            -166.41,
                            -269.14,
                            0.00865,
                            3,
                            1,
                            622.19,
                            331.95,
                            0.09351,
                            2,
                            -199.41,
                            55.48,
                            0.75711,
                            3,
                            -35.87,
                            -213.19,
                            0.14938,
                            4,
                            1,
                            662.88,
                            406.54,
                            0.01626,
                            2,
                            -158.72,
                            130.08,
                            0.38866,
                            3,
                            4.82,
                            -138.6,
                            0.59227,
                            4,
                            -444.27,
                            -339.78,
                            0.00281,
                            3,
                            1,
                            559.47,
                            408.23,
                            0.00101,
                            2,
                            -262.14,
                            131.77,
                            0.04675,
                            3,
                            -98.59,
                            -136.9,
                            0.95224,
                            1,
                            3,
                            -215.57,
                            -86.05,
                            1,
                            1,
                            3,
                            -115.55,
                            54.66,
                            1,
                            3,
                            2,
                            -114.64,
                            403.02,
                            0.00106,
                            3,
                            48.9,
                            134.34,
                            0.89206,
                            4,
                            -400.19,
                            -66.84,
                            0.10688,
                            3,
                            2,
                            34.54,
                            423.36,
                            0.01726,
                            3,
                            198.08,
                            154.69,
                            0.50375,
                            4,
                            -251.01,
                            -46.5,
                            0.47899,
                            3,
                            2,
                            163.38,
                            496.26,
                            0.00055,
                            3,
                            326.93,
                            227.58,
                            0.11324,
                            4,
                            -122.16,
                            26.4,
                            0.8862,
                            2,
                            3,
                            495.73,
                            352.75,
                            0,
                            4,
                            46.64,
                            151.57,
                            1,
                            3,
                            2,
                            332.19,
                            253.83,
                            0.00287,
                            3,
                            495.73,
                            -14.84,
                            0.10167,
                            4,
                            46.64,
                            -216.03,
                            0.89546,
                            3,
                            2,
                            243.06,
                            228.4,
                            0.01595,
                            3,
                            406.6,
                            -40.27,
                            0.16735,
                            4,
                            -42.49,
                            -241.45,
                            0.81671,
                            3,
                            2,
                            143.04,
                            216.54,
                            0.07162,
                            3,
                            306.58,
                            -52.14,
                            0.3175,
                            4,
                            -142.51,
                            -253.32,
                            0.61088,
                            3,
                            2,
                            59.97,
                            216.54,
                            0.25151,
                            3,
                            223.51,
                            -52.14,
                            0.43847,
                            4,
                            -225.58,
                            -253.32,
                            0.31002,
                            3,
                            2,
                            43.02,
                            199.55,
                            0.4443,
                            3,
                            206.56,
                            -69.13,
                            0.39095,
                            4,
                            -242.53,
                            -270.31,
                            0.16475,
                            3,
                            2,
                            126.7,
                            170.69,
                            0.84335,
                            3,
                            290.24,
                            -97.98,
                            0.1225,
                            4,
                            -158.85,
                            -299.17,
                            0.03415,
                            3,
                            2,
                            215.18,
                            125.49,
                            0.96496,
                            3,
                            378.72,
                            -143.19,
                            0.02814,
                            4,
                            -70.37,
                            -344.37,
                            0.0069,
                            3,
                            2,
                            244.04,
                            35.08,
                            0.99548,
                            3,
                            407.58,
                            -233.6,
                            0.00374,
                            4,
                            -41.51,
                            -434.78,
                            0.00078,
                            1,
                            2,
                            151.7,
                            -77.46,
                            1,
                            2,
                            1,
                            773.25,
                            138.41,
                            0.0292,
                            2,
                            -48.35,
                            -138.05,
                            0.9708,
                            3,
                            1,
                            600.12,
                            144.18,
                            0.18364,
                            2,
                            -221.48,
                            -132.28,
                            0.81045,
                            3,
                            -57.94,
                            -400.96,
                            0.00591,
                            2,
                            1,
                            445.27,
                            134.56,
                            0.43297,
                            2,
                            -376.33,
                            -141.9,
                            0.56703,
                            2,
                            1,
                            295.57,
                            80.77,
                            0.687,
                            2,
                            -526.03,
                            -195.7,
                            0.313,
                            2,
                            1,
                            180.15,
                            23.06,
                            0.85718,
                            2,
                            -641.45,
                            -253.41,
                            0.14282,
                            2,
                            1,
                            50.31,
                            -27.92,
                            0.98376,
                            2,
                            -771.29,
                            -304.38,
                            0.01624,
                            1,
                            1,
                            -58.38,
                            -36.11,
                            1,
                            4,
                            1,
                            756.7,
                            279.06,
                            0.02229,
                            2,
                            -64.9,
                            2.6,
                            0.91697,
                            3,
                            98.64,
                            -266.08,
                            0.06014,
                            4,
                            -350.45,
                            -467.26,
                            0.00059,
                            3,
                            2,
                            63.6,
                            61,
                            0.92422,
                            3,
                            227.14,
                            -207.67,
                            0.06334,
                            4,
                            -221.95,
                            -408.85,
                            0.01245,
                            4,
                            1,
                            767.09,
                            449.09,
                            0.0025,
                            2,
                            -54.51,
                            172.63,
                            0.41609,
                            3,
                            109.03,
                            -96.05,
                            0.52713,
                            4,
                            -340.06,
                            -297.23,
                            0.05427,
                            4,
                            1,
                            663.25,
                            529.56,
                            0.00031,
                            2,
                            -158.35,
                            253.1,
                            0.02328,
                            3,
                            5.19,
                            -15.58,
                            0.97589,
                            4,
                            -443.9,
                            -216.76,
                            0.00052
                        ],
                        "hull": 31
                    }
                }
            }
        }
    ],
    "animations": {
        "animation": {}
    },
    "extra": {
        "b11_yun_a": {
            "rootBoneName": "b11_yun_a",
            "animation": {
                "default": {
                    "name": "default",
                    "mode": 3,
                    "moveXFreq": 5,
                    "moveXAmp": 30,
                    "moveXOctaves": 0,
                    "moveXDelay": 0,
                    "moveXCenter": 0,
                    "moveXSeed": 1507,
                    "scaleXFreq": 6,
                    "scaleXAmp": 0.02,
                    "scaleXOctaves": 0,
                    "scaleXDelay": 0,
                    "scaleXCenter": 0
                }
            }
        },
        "b11_yun_a2": {
            "rootBoneName": "b11_yun_a2",
            "animation": {
                "default": {
                    "name": "default",
                    "mode": 3,
                    "moveXFreq": 5,
                    "moveXAmp": 30,
                    "moveXOctaves": 0,
                    "moveXDelay": 3.3368091921874465,
                    "moveXCenter": 0,
                    "moveXSeed": 1506.6570801130147,
                    "scaleXFreq": 6,
                    "scaleXAmp": 0.02,
                    "scaleXOctaves": 0,
                    "scaleXDelay": 2.4053124836299027,
                    "scaleXCenter": 0
                }
            }
        },
        "b11_yun_a3": {
            "rootBoneName": "b11_yun_a3",
            "animation": {
                "default": {
                    "name": "default",
                    "mode": 3,
                    "moveXFreq": 5,
                    "moveXAmp": 30,
                    "moveXOctaves": 0,
                    "moveXDelay": 5.139206628387178,
                    "moveXCenter": 0,
                    "moveXSeed": 1506.3431252222229,
                    "scaleXFreq": 6,
                    "scaleXAmp": 0.02,
                    "scaleXOctaves": 0,
                    "scaleXDelay": 4.102846718401815,
                    "scaleXCenter": 0
                }
            }
        },
        "b11_yun_a4": {
            "rootBoneName": "b11_yun_a4",
            "animation": {
                "default": {
                    "name": "default",
                    "mode": 3,
                    "moveXFreq": 5,
                    "moveXAmp": 30,
                    "moveXOctaves": 0,
                    "moveXDelay": 3.7900934155324784,
                    "moveXCenter": 0,
                    "moveXSeed": 1508.3194227659403,
                    "scaleXFreq": 6,
                    "scaleXAmp": 0.02,
                    "scaleXOctaves": 0,
                    "scaleXDelay": 6.153889687965367,
                    "scaleXCenter": 0
                }
            }
        }
    },
    "extraSlot": {},
    "extraConfig": {
        "timeScale": 1
    }
}